KNMI14ext/__init__.py
KNMI14ext/extract_KNMI14.py
KNMI14ext/quicksample.py
KNMI14ext-1.0.3.dist-info/LICENSE
KNMI14ext-1.0.3.dist-info/METADATA
KNMI14ext-1.0.3.dist-info/WHEEL
KNMI14ext-1.0.3.dist-info/top_level.txt
KNMI14ext-1.0.3.dist-info/RECORD
