Metadata-Version: 2.1
Name: KNMI14ext
Version: 1.0.3
Summary: Extraction KNMI14 test
Home-page: UNKNOWN
Author: X TIAN
Author-email: xin.tian@kwrwater.nl
License: UNKNOWN
Platform: UNKNOWN
Classifier: Programming Language :: Python :: 3
Classifier: License :: OSI Approved :: MIT License
Classifier: Operating System :: OS Independent
Requires-Python: >=3.7
License-File: LICENSE
Requires-Dist: numpy
Requires-Dist: pandas
